Metadata-Version: 1.1
Name: sqlalchemy-gbase8s
Version: 0.0.6
Summary: SQLAlchemy gbase8s backend
Home-page: https://github.com/dafei1288/sqlalchemy-gbase8s
Author: dafei1288
Author-email: lijiaqi@gbase.cn
License: MIT License
Keywords: SQLAlchemy,gbase8s
Platform: any
Classifier: Development Status :: 3 - Alpha
Classifier: Environment :: Console
Classifier: Intended Audience :: Developers
Classifier: Programming Language :: Python
Classifier: Programming Language :: Python :: 3
Classifier: Programming Language :: Python :: Implementation :: CPython
Classifier: Topic :: Database :: Front-Ends
